LICENSE.txt
MANIFEST.in
README.rst
setup.cfg
setup.py
gmaps/__init__.py
gmaps/_docutils.py
gmaps/_version.py
gmaps/bicycling.py
gmaps/bounds.py
gmaps/directions.py
gmaps/drawing.py
gmaps/errors_box.py
gmaps/figure.py
gmaps/geojson_layer.py
gmaps/geotraitlets.py
gmaps/heatmap.py
gmaps/locations.py
gmaps/maps.py
gmaps/marker.py
gmaps/options.py
gmaps/toolbar.py
gmaps/traffic.py
gmaps/transit.py
gmaps.egg-info/PKG-INFO
gmaps.egg-info/SOURCES.txt
gmaps.egg-info/dependency_links.txt
gmaps.egg-info/not-zip-safe
gmaps.egg-info/requires.txt
gmaps.egg-info/top_level.txt
gmaps/datasets/__init__.py
gmaps/datasets/datasets.py
gmaps/datasets/tests/__init__.py
gmaps/datasets/tests/test_datasets.py
gmaps/geojson_geometries/__init__.py
gmaps/geojson_geometries/geojson_geometries.py
gmaps/geojson_geometries/tests/__init__.py
gmaps/geojson_geometries/tests/test_geojson_geometries.py
gmaps/labextension/jupyter-gmaps-0.8.4.tgz
gmaps/static/722cf15958f56fd3875db7a4aa8b241a.eot
gmaps/static/extension.js
gmaps/static/index.js
gmaps/static/index.js.map
gmaps/tests/__init__.py
gmaps/tests/test_bounds.py
gmaps/tests/test_directions.py
gmaps/tests/test_drawing.py
gmaps/tests/test_errors_box.py
gmaps/tests/test_figure.py
gmaps/tests/test_geojson_layer.py
gmaps/tests/test_geotraitlets.py
gmaps/tests/test_heatmap.py
gmaps/tests/test_maps.py
gmaps/tests/test_marker.py
gmaps/tests/test_traffic.py