Metadata-Version: 1.1
Name: gmaps
Version: 0.8.4
Summary: Google maps plugin for Jupyter notebooks
Home-page: https://github.com/pbugnion/gmaps
Author: Pascal Bugnion
Author-email: pascal@bugnion.org
License: UNKNOWN
Keywords: ipython,jupyter,widgets
Platform: UNKNOWN
Classifier: Development Status :: 4 - Beta
Classifier: Framework :: IPython
Classifier: Intended Audience :: Developers
Classifier: Intended Audience :: Science/Research
Classifier: Topic :: Multimedia :: Graphics
Classifier: Programming Language :: Python :: 2
Classifier: Programming Language :: Python :: 2.7
Classifier: Programming Language :: Python :: 3
Classifier: Programming Language :: Python :: 3.5
Classifier: Programming Language :: Python :: 3.6
